{"file":"core/docs/how-to-guides/rolling-calculations.md","objects":{"source":{"type":"Table","data":{"columns":[{"name":"ID","type":"java.lang.String"},{"name":"Value","type":"long"}],"rows":[[{"value":"A"},{"value":"0"}],[{"value":"B"},{"value":"1"}],[{"value":"A"},{"value":"2"}],[{"value":"B"},{"value":"3"}],[{"value":"A"},{"value":"4"}],[{"value":"B"},{"value":"5"}],[{"value":"A"},{"value":"6"}],[{"value":"B"},{"value":"7"}],[{"value":"A"},{"value":"8"}],[{"value":"B"},{"value":"9"}],[{"value":"A"},{"value":"10"}],[{"value":"B"},{"value":"11"}],[{"value":"A"},{"value":"12"}],[{"value":"B"},{"value":"13"}],[{"value":"A"},{"value":"14"}],[{"value":"B"},{"value":"15"}],[{"value":"A"},{"value":"16"}],[{"value":"B"},{"value":"17"}],[{"value":"A"},{"value":"18"}],[{"value":"B"},{"value":"19"}],[{"value":"A"},{"value":"20"}],[{"value":"B"},{"value":"21"}],[{"value":"A"},{"value":"22"}],[{"value":"B"},{"value":"23"}],[{"value":"A"},{"value":"24"}],[{"value":"B"},{"value":"25"}],[{"value":"A"},{"value":"26"}],[{"value":"B"},{"value":"27"}],[{"value":"A"},{"value":"28"}],[{"value":"B"},{"value":"29"}],[{"value":"A"},{"value":"30"}],[{"value":"B"},{"value":"31"}],[{"value":"A"},{"value":"32"}],[{"value":"B"},{"value":"33"}],[{"value":"A"},{"value":"34"}],[{"value":"B"},{"value":"35"}],[{"value":"A"},{"value":"36"}],[{"value":"B"},{"value":"37"}],[{"value":"A"},{"value":"38"}],[{"value":"B"},{"value":"39"}],[{"value":"A"},{"value":"40"}],[{"value":"B"},{"value":"41"}],[{"value":"A"},{"value":"42"}],[{"value":"B"},{"value":"43"}],[{"value":"A"},{"value":"44"}],[{"value":"B"},{"value":"45"}],[{"value":"A"},{"value":"46"}],[{"value":"B"},{"value":"47"}],[{"value":"A"},{"value":"48"}],[{"value":"B"},{"value":"49"}]]}},"result":{"type":"Table","data":{"columns":[{"name":"ID","type":"java.lang.String"},{"name":"Value","type":"long"},{"name":"Group","type":"java.lang.String"}],"rows":[[{"value":"A"},{"value":"0"},{"value":"[0]"}],[{"value":"B"},{"value":"1"},{"value":"[1]"}],[{"value":"A"},{"value":"2"},{"value":"[0,2]"}],[{"value":"B"},{"value":"3"},{"value":"[1,3]"}],[{"value":"A"},{"value":"4"},{"value":"[0,2,4]"}],[{"value":"B"},{"value":"5"},{"value":"[1,3,5]"}],[{"value":"A"},{"value":"6"},{"value":"[0,2,4,6]"}],[{"value":"B"},{"value":"7"},{"value":"[1,3,5,7]"}],[{"value":"A"},{"value":"8"},{"value":"[2,4,6,8]"}],[{"value":"B"},{"value":"9"},{"value":"[3,5,7,9]"}],[{"value":"A"},{"value":"10"},{"value":"[4,6,8,10]"}],[{"value":"B"},{"value":"11"},{"value":"[5,7,9,11]"}],[{"value":"A"},{"value":"12"},{"value":"[6,8,10,12]"}],[{"value":"B"},{"value":"13"},{"value":"[7,9,11,13]"}],[{"value":"A"},{"value":"14"},{"value":"[8,10,12,14]"}],[{"value":"B"},{"value":"15"},{"value":"[9,11,13,15]"}],[{"value":"A"},{"value":"16"},{"value":"[10,12,14,16]"}],[{"value":"B"},{"value":"17"},{"value":"[11,13,15,17]"}],[{"value":"A"},{"value":"18"},{"value":"[12,14,16,18]"}],[{"value":"B"},{"value":"19"},{"value":"[13,15,17,19]"}],[{"value":"A"},{"value":"20"},{"value":"[14,16,18,20]"}],[{"value":"B"},{"value":"21"},{"value":"[15,17,19,21]"}],[{"value":"A"},{"value":"22"},{"value":"[16,18,20,22]"}],[{"value":"B"},{"value":"23"},{"value":"[17,19,21,23]"}],[{"value":"A"},{"value":"24"},{"value":"[18,20,22,24]"}],[{"value":"B"},{"value":"25"},{"value":"[19,21,23,25]"}],[{"value":"A"},{"value":"26"},{"value":"[20,22,24,26]"}],[{"value":"B"},{"value":"27"},{"value":"[21,23,25,27]"}],[{"value":"A"},{"value":"28"},{"value":"[22,24,26,28]"}],[{"value":"B"},{"value":"29"},{"value":"[23,25,27,29]"}],[{"value":"A"},{"value":"30"},{"value":"[24,26,28,30]"}],[{"value":"B"},{"value":"31"},{"value":"[25,27,29,31]"}],[{"value":"A"},{"value":"32"},{"value":"[26,28,30,32]"}],[{"value":"B"},{"value":"33"},{"value":"[27,29,31,33]"}],[{"value":"A"},{"value":"34"},{"value":"[28,30,32,34]"}],[{"value":"B"},{"value":"35"},{"value":"[29,31,33,35]"}],[{"value":"A"},{"value":"36"},{"value":"[30,32,34,36]"}],[{"value":"B"},{"value":"37"},{"value":"[31,33,35,37]"}],[{"value":"A"},{"value":"38"},{"value":"[32,34,36,38]"}],[{"value":"B"},{"value":"39"},{"value":"[33,35,37,39]"}],[{"value":"A"},{"value":"40"},{"value":"[34,36,38,40]"}],[{"value":"B"},{"value":"41"},{"value":"[35,37,39,41]"}],[{"value":"A"},{"value":"42"},{"value":"[36,38,40,42]"}],[{"value":"B"},{"value":"43"},{"value":"[37,39,41,43]"}],[{"value":"A"},{"value":"44"},{"value":"[38,40,42,44]"}],[{"value":"B"},{"value":"45"},{"value":"[39,41,43,45]"}],[{"value":"A"},{"value":"46"},{"value":"[40,42,44,46]"}],[{"value":"B"},{"value":"47"},{"value":"[41,43,45,47]"}],[{"value":"A"},{"value":"48"},{"value":"[42,44,46,48]"}],[{"value":"B"},{"value":"49"},{"value":"[43,45,47,49]"}]]}}}}