{"file":"conceptual/vectorization-and-recipes.md","objects":{"dh_result":{"type":"Table","data":{"columns":[{"name":"X","type":"long"},{"name":"XSquared","type":"long"}],"rows":[[{"value":"0"},{"value":"0"}],[{"value":"1"},{"value":"1"}],[{"value":"2"},{"value":"4"}],[{"value":"3"},{"value":"9"}],[{"value":"4"},{"value":"16"}],[{"value":"5"},{"value":"25"}],[{"value":"6"},{"value":"36"}],[{"value":"7"},{"value":"49"}],[{"value":"8"},{"value":"64"}],[{"value":"9"},{"value":"81"}],[{"value":"10"},{"value":"100"}],[{"value":"11"},{"value":"121"}],[{"value":"12"},{"value":"144"}],[{"value":"13"},{"value":"169"}],[{"value":"14"},{"value":"196"}],[{"value":"15"},{"value":"225"}],[{"value":"16"},{"value":"256"}],[{"value":"17"},{"value":"289"}],[{"value":"18"},{"value":"324"}],[{"value":"19"},{"value":"361"}],[{"value":"20"},{"value":"400"}],[{"value":"21"},{"value":"441"}],[{"value":"22"},{"value":"484"}],[{"value":"23"},{"value":"529"}],[{"value":"24"},{"value":"576"}],[{"value":"25"},{"value":"625"}],[{"value":"26"},{"value":"676"}],[{"value":"27"},{"value":"729"}],[{"value":"28"},{"value":"784"}],[{"value":"29"},{"value":"841"}],[{"value":"30"},{"value":"900"}],[{"value":"31"},{"value":"961"}],[{"value":"32"},{"value":"1,024"}],[{"value":"33"},{"value":"1,089"}],[{"value":"34"},{"value":"1,156"}],[{"value":"35"},{"value":"1,225"}],[{"value":"36"},{"value":"1,296"}],[{"value":"37"},{"value":"1,369"}],[{"value":"38"},{"value":"1,444"}],[{"value":"39"},{"value":"1,521"}],[{"value":"40"},{"value":"1,600"}],[{"value":"41"},{"value":"1,681"}],[{"value":"42"},{"value":"1,764"}],[{"value":"43"},{"value":"1,849"}],[{"value":"44"},{"value":"1,936"}],[{"value":"45"},{"value":"2,025"}],[{"value":"46"},{"value":"2,116"}],[{"value":"47"},{"value":"2,209"}],[{"value":"48"},{"value":"2,304"}],[{"value":"49"},{"value":"2,401"}],[{"value":"50"},{"value":"2,500"}],[{"value":"51"},{"value":"2,601"}],[{"value":"52"},{"value":"2,704"}],[{"value":"53"},{"value":"2,809"}],[{"value":"54"},{"value":"2,916"}],[{"value":"55"},{"value":"3,025"}],[{"value":"56"},{"value":"3,136"}],[{"value":"57"},{"value":"3,249"}],[{"value":"58"},{"value":"3,364"}],[{"value":"59"},{"value":"3,481"}],[{"value":"60"},{"value":"3,600"}],[{"value":"61"},{"value":"3,721"}],[{"value":"62"},{"value":"3,844"}],[{"value":"63"},{"value":"3,969"}],[{"value":"64"},{"value":"4,096"}],[{"value":"65"},{"value":"4,225"}],[{"value":"66"},{"value":"4,356"}],[{"value":"67"},{"value":"4,489"}],[{"value":"68"},{"value":"4,624"}],[{"value":"69"},{"value":"4,761"}],[{"value":"70"},{"value":"4,900"}],[{"value":"71"},{"value":"5,041"}],[{"value":"72"},{"value":"5,184"}],[{"value":"73"},{"value":"5,329"}],[{"value":"74"},{"value":"5,476"}],[{"value":"75"},{"value":"5,625"}],[{"value":"76"},{"value":"5,776"}],[{"value":"77"},{"value":"5,929"}],[{"value":"78"},{"value":"6,084"}],[{"value":"79"},{"value":"6,241"}],[{"value":"80"},{"value":"6,400"}],[{"value":"81"},{"value":"6,561"}],[{"value":"82"},{"value":"6,724"}],[{"value":"83"},{"value":"6,889"}],[{"value":"84"},{"value":"7,056"}],[{"value":"85"},{"value":"7,225"}],[{"value":"86"},{"value":"7,396"}],[{"value":"87"},{"value":"7,569"}],[{"value":"88"},{"value":"7,744"}],[{"value":"89"},{"value":"7,921"}],[{"value":"90"},{"value":"8,100"}],[{"value":"91"},{"value":"8,281"}],[{"value":"92"},{"value":"8,464"}],[{"value":"93"},{"value":"8,649"}],[{"value":"94"},{"value":"8,836"}],[{"value":"95"},{"value":"9,025"}],[{"value":"96"},{"value":"9,216"}],[{"value":"97"},{"value":"9,409"}],[{"value":"98"},{"value":"9,604"}],[{"value":"99"},{"value":"9,801"}]]}},"_":{"type":"Table","data":{"columns":[{"name":"X","type":"long"},{"name":"XSquared","type":"long"}],"rows":[[{"value":"0"},{"value":"0"}]]}},":log":{"type":"Log","data":"Loop approach: 0.2039 seconds\nRecipe approach: 0.0734 seconds\nSpeedup: 2.78x\n"}}}