{"file":"core/docs/reference/table-operations/update-by-operations/cum-min.md","objects":{"source":{"type":"Table","data":{"columns":[{"name":"Letter","type":"java.lang.String"},{"name":"X","type":"int"}],"rows":[[{"value":"A"},{"value":"16"}],[{"value":"B"},{"value":"22"}],[{"value":"A"},{"value":"6"}],[{"value":"B"},{"value":"23"}],[{"value":"A"},{"value":"14"}],[{"value":"B"},{"value":"10"}],[{"value":"A"},{"value":"6"}],[{"value":"B"},{"value":"11"}],[{"value":"A"},{"value":"20"}],[{"value":"B"},{"value":"2"}],[{"value":"A"},{"value":"16"}],[{"value":"B"},{"value":"19"}],[{"value":"A"},{"value":"24"}],[{"value":"B"},{"value":"5"}],[{"value":"A"},{"value":"19"}],[{"value":"B"},{"value":"11"}],[{"value":"A"},{"value":"2"}],[{"value":"B"},{"value":"12"}],[{"value":"A"},{"value":"13"}],[{"value":"B"},{"value":"17"}],[{"value":"A"},{"value":"15"}],[{"value":"B"},{"value":"20"}],[{"value":"A"},{"value":"21"}],[{"value":"B"},{"value":"7"}],[{"value":"A"},{"value":"18"}]]}},"result":{"type":"Table","data":{"columns":[{"name":"Letter","type":"java.lang.String"},{"name":"X","type":"int"},{"name":"MinX","type":"int"}],"rows":[[{"value":"A"},{"value":"16"},{"value":"16"}],[{"value":"B"},{"value":"22"},{"value":"22"}],[{"value":"A"},{"value":"6"},{"value":"6"}],[{"value":"B"},{"value":"23"},{"value":"22"}],[{"value":"A"},{"value":"14"},{"value":"6"}],[{"value":"B"},{"value":"10"},{"value":"10"}],[{"value":"A"},{"value":"6"},{"value":"6"}],[{"value":"B"},{"value":"11"},{"value":"10"}],[{"value":"A"},{"value":"20"},{"value":"6"}],[{"value":"B"},{"value":"2"},{"value":"2"}],[{"value":"A"},{"value":"16"},{"value":"6"}],[{"value":"B"},{"value":"19"},{"value":"2"}],[{"value":"A"},{"value":"24"},{"value":"6"}],[{"value":"B"},{"value":"5"},{"value":"2"}],[{"value":"A"},{"value":"19"},{"value":"6"}],[{"value":"B"},{"value":"11"},{"value":"2"}],[{"value":"A"},{"value":"2"},{"value":"2"}],[{"value":"B"},{"value":"12"},{"value":"2"}],[{"value":"A"},{"value":"13"},{"value":"2"}],[{"value":"B"},{"value":"17"},{"value":"2"}],[{"value":"A"},{"value":"15"},{"value":"2"}],[{"value":"B"},{"value":"20"},{"value":"2"}],[{"value":"A"},{"value":"21"},{"value":"2"}],[{"value":"B"},{"value":"7"},{"value":"2"}],[{"value":"A"},{"value":"18"},{"value":"2"}]]}}}}