{"file":"core/docs/how-to-guides/use-lastby.md","objects":{"t":{"type":"Table","data":{"columns":[{"name":"MyKey","type":"java.lang.String"},{"name":"MySecondKey","type":"long"},{"name":"MyCol","type":"long"}],"rows":[[{"value":"A"},{"value":"0"},{"value":"0"}],[{"value":"B"},{"value":"1"},{"value":"1"}],[{"value":"C"},{"value":"0"},{"value":"2"}],[{"value":"D"},{"value":"1"},{"value":"3"}],[{"value":"E"},{"value":"0"},{"value":"4"}],[{"value":"A"},{"value":"1"},{"value":"5"}],[{"value":"B"},{"value":"0"},{"value":"6"}],[{"value":"C"},{"value":"1"},{"value":"7"}],[{"value":"D"},{"value":"0"},{"value":"8"}],[{"value":"E"},{"value":"1"},{"value":"9"}]]}},"t2":{"type":"Table","data":{"columns":[{"name":"MyKey","type":"java.lang.String"},{"name":"MySecondKey","type":"long"},{"name":"MyCol","type":"long"}],"rows":[[{"value":"A"},{"value":"0"},{"value":"0"}],[{"value":"B"},{"value":"1"},{"value":"1"}],[{"value":"C"},{"value":"0"},{"value":"2"}],[{"value":"D"},{"value":"1"},{"value":"3"}],[{"value":"E"},{"value":"0"},{"value":"4"}],[{"value":"A"},{"value":"1"},{"value":"5"}],[{"value":"B"},{"value":"0"},{"value":"6"}],[{"value":"C"},{"value":"1"},{"value":"7"}],[{"value":"D"},{"value":"0"},{"value":"8"}],[{"value":"E"},{"value":"1"},{"value":"9"}]]}}}}