{"file":"core_versioned_docs/version-groovy/docs/how-to-guides/other-rolling-utils.md","objects":{"source":{"type":"Table","data":{"columns":[{"name":"Letter","type":"java.lang.String"},{"name":"X","type":"int"}],"rows":[[{"value":"A"},{"value":"76"}],[{"value":"B"},{"value":"11"}],[{"value":"A"},{"value":"24"}],[{"value":"B"},{"value":"1"}],[{"value":"A"},{"value":"46"}],[{"value":"B"},{"value":"71"}],[{"value":"A"},{"value":"64"}],[{"value":"B"},{"value":"75"}],[{"value":"A"},{"value":"93"}],[{"value":"B"},{"value":"70"}],[{"value":"A"},{"value":"2"}],[{"value":"B"},{"value":"69"}],[{"value":"A"},{"value":"76"}],[{"value":"B"},{"value":"50"}],[{"value":"A"},{"value":"38"}],[{"value":"B"},{"value":"1"}],[{"value":"A"},{"value":"33"}],[{"value":"B"},{"value":"20"}],[{"value":"A"},{"value":"21"}],[{"value":"B"},{"value":"60"}],[{"value":"A"},{"value":"10"}],[{"value":"B"},{"value":"59"}],[{"value":"A"},{"value":"50"}],[{"value":"B"},{"value":"85"}],[{"value":"A"},{"value":"61"}],[{"value":"B"},{"value":"48"}],[{"value":"A"},{"value":"91"}],[{"value":"B"},{"value":"63"}],[{"value":"A"},{"value":"83"}],[{"value":"B"},{"value":"20"}],[{"value":"A"},{"value":"85"}],[{"value":"B"},{"value":"20"}],[{"value":"A"},{"value":"41"}],[{"value":"B"},{"value":"37"}],[{"value":"A"},{"value":"11"}],[{"value":"B"},{"value":"94"}],[{"value":"A"},{"value":"28"}],[{"value":"B"},{"value":"15"}],[{"value":"A"},{"value":"57"}],[{"value":"B"},{"value":"36"}],[{"value":"A"},{"value":"91"}],[{"value":"B"},{"value":"28"}],[{"value":"A"},{"value":"84"}],[{"value":"B"},{"value":"99"}],[{"value":"A"},{"value":"14"}],[{"value":"B"},{"value":"8"}],[{"value":"A"},{"value":"67"}],[{"value":"B"},{"value":"64"}],[{"value":"A"},{"value":"55"}],[{"value":"B"},{"value":"82"}],[{"value":"A"},{"value":"9"}],[{"value":"B"},{"value":"68"}],[{"value":"A"},{"value":"34"}],[{"value":"B"},{"value":"60"}],[{"value":"A"},{"value":"31"}],[{"value":"B"},{"value":"45"}],[{"value":"A"},{"value":"21"}],[{"value":"B"},{"value":"42"}],[{"value":"A"},{"value":"5"}],[{"value":"B"},{"value":"45"}],[{"value":"A"},{"value":"94"}],[{"value":"B"},{"value":"74"}],[{"value":"A"},{"value":"76"}],[{"value":"B"},{"value":"50"}],[{"value":"A"},{"value":"51"}],[{"value":"B"},{"value":"36"}],[{"value":"A"},{"value":"79"}],[{"value":"B"},{"value":"17"}],[{"value":"A"},{"value":"51"}],[{"value":"B"},{"value":"64"}],[{"value":"A"},{"value":"73"}],[{"value":"B"},{"value":"96"}],[{"value":"A"},{"value":"71"}],[{"value":"B"},{"value":"62"}],[{"value":"A"},{"value":"63"}],[{"value":"B"},{"value":"3"}],[{"value":"A"},{"value":"75"}],[{"value":"B"},{"value":"81"}],[{"value":"A"},{"value":"66"}],[{"value":"B"},{"value":"11"}],[{"value":"A"},{"value":"92"}],[{"value":"B"},{"value":"44"}],[{"value":"A"},{"value":"82"}],[{"value":"B"},{"value":"63"}],[{"value":"A"},{"value":"41"}],[{"value":"B"},{"value":"31"}],[{"value":"A"},{"value":"9"}],[{"value":"B"},{"value":"96"}],[{"value":"A"},{"value":"99"}],[{"value":"B"},{"value":"88"}],[{"value":"A"},{"value":"87"}],[{"value":"B"},{"value":"28"}],[{"value":"A"},{"value":"58"}],[{"value":"B"},{"value":"43"}],[{"value":"A"},{"value":"48"}],[{"value":"B"},{"value":"44"}],[{"value":"A"},{"value":"11"}],[{"value":"B"},{"value":"55"}],[{"value":"A"},{"value":"34"}],[{"value":"B"},{"value":"47"}]]}},"result":{"type":"Table","data":{"columns":[{"name":"Letter","type":"java.lang.String"},{"name":"X","type":"int"},{"name":"GeomMeanX","type":"double"}],"rows":[[{"value":"A"},{"value":"76"},{"value":"76.0000"}],[{"value":"B"},{"value":"11"},{"value":"11.0000"}],[{"value":"A"},{"value":"24"},{"value":"42.7083"}],[{"value":"B"},{"value":"1"},{"value":"3.3166"}],[{"value":"A"},{"value":"46"},{"value":"43.7785"}],[{"value":"B"},{"value":"71"},{"value":"9.2091"}],[{"value":"A"},{"value":"64"},{"value":"41.3412"}],[{"value":"B"},{"value":"75"},{"value":"17.4625"}],[{"value":"A"},{"value":"93"},{"value":"64.9342"}],[{"value":"B"},{"value":"70"},{"value":"71.9680"}],[{"value":"A"},{"value":"2"},{"value":"22.8331"}],[{"value":"B"},{"value":"69"},{"value":"71.2858"}],[{"value":"A"},{"value":"76"},{"value":"24.1792"}],[{"value":"B"},{"value":"50"},{"value":"62.2738"}],[{"value":"A"},{"value":"38"},{"value":"17.9422"}],[{"value":"B"},{"value":"1"},{"value":"15.1103"}],[{"value":"A"},{"value":"33"},{"value":"45.6776"}],[{"value":"B"},{"value":"20"},{"value":"10.0000"}],[{"value":"A"},{"value":"21"},{"value":"29.7513"}],[{"value":"B"},{"value":"60"},{"value":"10.6266"}],[{"value":"A"},{"value":"10"},{"value":"19.0653"}],[{"value":"B"},{"value":"59"},{"value":"41.3693"}],[{"value":"A"},{"value":"50"},{"value":"21.8976"}],[{"value":"B"},{"value":"85"},{"value":"67.0102"}],[{"value":"A"},{"value":"61"},{"value":"31.2440"}],[{"value":"B"},{"value":"48"},{"value":"62.2067"}],[{"value":"A"},{"value":"91"},{"value":"65.2300"}],[{"value":"B"},{"value":"63"},{"value":"63.5819"}],[{"value":"A"},{"value":"83"},{"value":"77.2354"}],[{"value":"B"},{"value":"20"},{"value":"39.2528"}],[{"value":"A"},{"value":"85"},{"value":"86.2673"}],[{"value":"B"},{"value":"20"},{"value":"29.3179"}],[{"value":"A"},{"value":"41"},{"value":"66.1343"}],[{"value":"B"},{"value":"37"},{"value":"24.5520"}],[{"value":"A"},{"value":"11"},{"value":"33.7183"}],[{"value":"B"},{"value":"94"},{"value":"41.1263"}],[{"value":"A"},{"value":"28"},{"value":"23.2869"}],[{"value":"B"},{"value":"15"},{"value":"37.3657"}],[{"value":"A"},{"value":"57"},{"value":"25.9901"}],[{"value":"B"},{"value":"36"},{"value":"37.0260"}],[{"value":"A"},{"value":"91"},{"value":"52.5644"}],[{"value":"B"},{"value":"28"},{"value":"24.7277"}],[{"value":"A"},{"value":"84"},{"value":"75.8109"}],[{"value":"B"},{"value":"99"},{"value":"46.3837"}],[{"value":"A"},{"value":"14"},{"value":"47.4770"}],[{"value":"B"},{"value":"8"},{"value":"28.0949"}],[{"value":"A"},{"value":"67"},{"value":"42.8707"}],[{"value":"B"},{"value":"64"},{"value":"37.0085"}],[{"value":"A"},{"value":"55"},{"value":"37.2268"}],[{"value":"B"},{"value":"82"},{"value":"34.7559"}],[{"value":"A"},{"value":"9"},{"value":"32.1287"}],[{"value":"B"},{"value":"68"},{"value":"70.9307"}],[{"value":"A"},{"value":"34"},{"value":"25.6268"}],[{"value":"B"},{"value":"60"},{"value":"69.4211"}],[{"value":"A"},{"value":"31"},{"value":"21.1687"}],[{"value":"B"},{"value":"45"},{"value":"56.8361"}],[{"value":"A"},{"value":"21"},{"value":"28.0772"}],[{"value":"B"},{"value":"42"},{"value":"48.4029"}],[{"value":"A"},{"value":"5"},{"value":"14.8201"}],[{"value":"B"},{"value":"45"},{"value":"43.9769"}],[{"value":"A"},{"value":"94"},{"value":"21.4506"}],[{"value":"B"},{"value":"74"},{"value":"51.9076"}],[{"value":"A"},{"value":"76"},{"value":"32.9334"}],[{"value":"B"},{"value":"50"},{"value":"55.0138"}],[{"value":"A"},{"value":"51"},{"value":"71.4229"}],[{"value":"B"},{"value":"36"},{"value":"51.0703"}],[{"value":"A"},{"value":"79"},{"value":"67.4016"}],[{"value":"B"},{"value":"17"},{"value":"31.2781"}],[{"value":"A"},{"value":"51"},{"value":"59.0096"}],[{"value":"B"},{"value":"64"},{"value":"33.9607"}],[{"value":"A"},{"value":"73"},{"value":"66.5028"}],[{"value":"B"},{"value":"96"},{"value":"47.0941"}],[{"value":"A"},{"value":"71"},{"value":"64.1776"}],[{"value":"B"},{"value":"62"},{"value":"72.4905"}],[{"value":"A"},{"value":"63"},{"value":"68.8611"}],[{"value":"B"},{"value":"3"},{"value":"26.1373"}],[{"value":"A"},{"value":"75"},{"value":"69.4843"}],[{"value":"B"},{"value":"81"},{"value":"24.6982"}],[{"value":"A"},{"value":"66"},{"value":"67.8134"}],[{"value":"B"},{"value":"11"},{"value":"13.8782"}],[{"value":"A"},{"value":"92"},{"value":"76.9362"}],[{"value":"B"},{"value":"44"},{"value":"33.9711"}],[{"value":"A"},{"value":"82"},{"value":"79.2590"}],[{"value":"B"},{"value":"63"},{"value":"31.2413"}],[{"value":"A"},{"value":"41"},{"value":"67.6283"}],[{"value":"B"},{"value":"31"},{"value":"44.1284"}],[{"value":"A"},{"value":"9"},{"value":"31.1611"}],[{"value":"B"},{"value":"96"},{"value":"57.2345"}],[{"value":"A"},{"value":"99"},{"value":"33.1808"}],[{"value":"B"},{"value":"88"},{"value":"63.9792"}],[{"value":"A"},{"value":"87"},{"value":"42.6382"}],[{"value":"B"},{"value":"28"},{"value":"61.8449"}],[{"value":"A"},{"value":"58"},{"value":"79.3464"}],[{"value":"B"},{"value":"43"},{"value":"47.3191"}],[{"value":"A"},{"value":"48"},{"value":"62.3346"}],[{"value":"B"},{"value":"44"},{"value":"37.5572"}],[{"value":"A"},{"value":"11"},{"value":"31.2863"}],[{"value":"B"},{"value":"55"},{"value":"47.0357"}],[{"value":"A"},{"value":"34"},{"value":"26.1841"}],[{"value":"B"},{"value":"47"},{"value":"48.4512"}]]}}}}